ouster/cli/plugins/cli_mapping_impl.py
ouster/cli/plugins/cli_source_mapping.py
ouster/mapping/__about__.py
ouster/mapping/__init__.py
ouster/mapping/kiss_backend.py
ouster/mapping/ouster_kiss_icp.py
ouster/mapping/ply_to_png.py
ouster/mapping/slam.py
ouster/mapping/slam_backend.py
ouster/mapping/util.py
ouster_mapping-0.2.1.dist-info/METADATA
ouster_mapping-0.2.1.dist-info/WHEEL
ouster_mapping-0.2.1.dist-info/RECORD
