Metadata-Version: 2.3
Name: ouster-mapping
Version: 0.2.1
Summary: Library to perform basic SLAM with Ouster lidars
Author-email: Tomas Svarovsky <tomas.svarovsky@ouster.io>
License-Expression: MIT
Classifier: Programming Language :: Python :: 3.8
Classifier: Programming Language :: Python :: 3.9
Classifier: Programming Language :: Python :: 3.10
Classifier: Programming Language :: Python :: 3.11
Classifier: Programming Language :: Python :: 3.12
Requires-Python: >=3.8
Requires-Dist: kiss-icp==0.4.0; platform_machine != 'aarch64'
Requires-Dist: laspy<3,>=2.5.0
Requires-Dist: numpy!=1.19.4,<2,>=1.19
Requires-Dist: ouster-sdk==0.11.1
Requires-Dist: point-cloud-utils<1,>=0.30.4; python_version <= '3.11' and platform_machine != 'aarch64' and (platform_system != 'Darwin' or platform_machine != 'arm64' or platform_version >= '21.0.0')
